bfd/__init__.py
bfd/client.py
bfd/exceptions.py
bfd/http.py
bfd/objects.py
bfd.py-1.0.2.dist-info/METADATA
bfd.py-1.0.2.dist-info/RECORD
bfd.py-1.0.2.dist-info/WHEEL
bfd.py-1.0.2.dist-info/top_level.txt
