Metadata-Version: 2.1
Name: bfd.py
Version: 1.0.2
Summary: A simple API wrapper for botsfordiscord.com written in Python.
Home-page: https://github.com/MattIPv4/bfd.py/
Author: MattIPv4
License: UNKNOWN
Project-URL: Funding, http://patreon.mattcowley.co.uk/
Project-URL: Support, http://discord.mattcowley.co.uk/
Project-URL: Source, https://github.com/MattIPv4/bfd.py/
Keywords: api wrapper discord bot bots stats statistics
Platform: UNKNOWN
Classifier: License :: OSI Approved :: GNU Affero General Public License v3
Classifier: Programming Language :: Python :: 3
Classifier: Natural Language :: English
Classifier: Intended Audience :: Developers
Classifier: Operating System :: OS Independent
Requires-Python: >= 3.5
Requires-Dist: aiohttp (>=2.3.9)
